linkdb.py
linkdb-0.1.1.dist-info/METADATA
linkdb-0.1.1.dist-info/WHEEL
linkdb-0.1.1.dist-info/entry_points.txt
linkdb-0.1.1.dist-info/licenses/LICENSE
linkdb-0.1.1.dist-info/RECORD
