Metadata-Version: 2.4
Name: linkdb
Version: 0.1.1
Summary: A zero-dependency CLI tool for managing curated project lists - zero dependencies, stdlib only
License-File: LICENSE
Requires-Python: >=3.8
